ExtraFerm-0.1.0.dist-info/METADATA
ExtraFerm-0.1.0.dist-info/WHEEL
ExtraFerm-0.1.0.dist-info/licenses/LICENSE
extraferm/__init__.py
extraferm/_lib.cpython-312-darwin.so
extraferm/_lib.py
extraferm/estimation.py
extraferm/exact.py
extraferm/interface.py
extraferm/raw_estimation.py
extraferm/utils.py
extraferm/utils_dev.py
ExtraFerm-0.1.0.dist-info/RECORD
