Metadata-Version: 2.4
Name: ExtraFerm
Version: 0.1.0
Requires-Dist: numpy>=2.3.2
Requires-Dist: scipy>=1.16.0
Requires-Dist: qiskit>=2.0.2
Requires-Dist: pytest>=8.4.0 ; extra == 'dev'
Requires-Dist: maturin>=1.0 ; extra == 'dev'
Requires-Dist: ffsim>=0.0.60 ; extra == 'dev'
Provides-Extra: dev
License-File: LICENSE
Summary: Quantum circuit simulator for particle number conserving extended matchgate circuits
Requires-Python: >=3.11
